release_extractor/__init__.py
release_extractor/main.py
release_extractor/prompts.py
release_extractor-2025.12.22081104.dist-info/METADATA
release_extractor-2025.12.22081104.dist-info/WHEEL
release_extractor-2025.12.22081104.dist-info/top_level.txt
release_extractor-2025.12.22081104.dist-info/RECORD
