Metadata-Version: 2.4
Name: release-extractor
Version: 2025.12.22081104
Summary: Extracts key release details from unstructured text to create clear, structured summaries.
Author-email: release-extractor <hi@eugene.plus>
License: MIT
Project-URL: Homepage, https://github.com/chigwell/release-extractor
Requires-Python: >=3.9
Requires-Dist: langchain-llm7>=0.0.0
Requires-Dist: llmatch-messages>=0.0.0
Requires-Dist: langchain-core>=0.3.0
